{
  "AliasWithColon": "(alias: {0})",
  "AuthClearComplete": "Autentiseringsprofiler och cachelagrad token har tagits bort",
  "AuthClearHelp": "Rensa alla autentiseringsprofiler som lagras på den här datorn",
  "AuthCreateHelp": "Skapa och lagra autentiseringsprofiler på den här datorn",
  "AuthCreateKindHelp": "Den typ av autentiseringsprofil som du skapar får standardvärdet CDS",
  "AuthCreateKindValidationHelp": "Värdet {0} som skickats för {1} är inte giltigt. Giltiga typer: {2}.",
  "AuthCreateResourceHelp": "Resurs-URL för att ansluta till",
  "AuthCreateResourceValidationHelp": "Värdet {0} som skickats för {1} är inte en giltig URL eller Guid.",
  "AuthCreateSuccess": "Autentiseringen har skapats.",
  "AuthDeleteHeader": "Borttagen profil:",
  "AuthDeleteHelp": "Ta bort en viss autentiseringsprofil",
  "AuthDeleteIndexHelp": "Index för den profil som ska tas bort",
  "AuthHelp": "Hantera hur du autentiserar till olika tjänster",
  "AuthListHeader": "Profiler (* anger att den är aktiv):",
  "AuthListHelp": "Listan med autentiseringsprofiler som lagras på den här datorn",
  "AuthListNoProfiles": "Det finns inga profiler på den här datorn. Kör {0} för att skapa en.",
  "AuthNameHeader": "Följande profil har namngetts:",
  "AuthNameHelp": "Namnge eller byt namn på en befintlig autentiseringsnyckel",
  "AuthNameIndexHelp": "Index för den profil som ska namnges/byta namn",
  "AuthNameInvalidLength": "Längden på namnet måste vara mellan 1 och 12.",
  "AuthNameNameHelp": "Namnet som du vill ge den här autentiseringsprofilen (högst 12 tecken)",
  "AuthNameProfileFailure": "De aktuella profilerna på datorn innehåller dubbletter. Kör {0} och skapa sedan nya profiler.",
  "AuthNoAuthority": "Det går inte att hämta domänadressen för URL:en {0}",
  "AuthProfileExpired": "(utgick för {0} minuter sedan)",
  "AuthProfileExpiresIn": "(utgår om {0} minuter)",
  "AuthProfileInvalid": "Den aktuella profilen har ofullständig information. Den kan ha skapats med en äldre version av CLI. Kör {0} och skapa sedan en ny profil.",
  "AuthProfileNameAlreadyExist": "Namnet som anges finns redan.",
  "AuthProfileNameDoesNotExist": "Det finns ingen autentiseringsprofil med namnet {0}",
  "AuthProfileNoneOfKind": "Det finns inga profiler av typen {0} på den här datorn. Kör {1} för att skapa en.",
  "AuthSelectHeader": "Ny standardprofil:",
  "AuthSelectHelp": "Välj vilken autentiseringsprofil som ska vara aktiv",
  "AuthSelectIndexHelp": "Index för den profil som ska vara aktiv",
  "AuthSelectIndexNotValid": "Värdet {0} för {1} är ogiltigt. Det måste ligga mellan 1 och {2}.",
  "AuthSelectNameHelp": "Namnet på den profil som ska vara aktiv",
  "AuthSelectNoIndexOrNameProvided": "Inget index eller namn har angetts",
  "AuthValidatingConnection": "Verifierar anslutning ...",
  "CannotProcessCommand": "{0} användes, men det föregående kommandot vet inte hur detta ska bearbetas.",
  "CdsAuthKindValidationUrlNotValid": "Den URL som skickades, {0}, är inte en giltig CDS-URL. URL:er måste använda säkra HTTPS-protokoll.",
  "CliHelpHelp": "Visa hjälp för Microsoft PowerApps CLI",
  "CliTelemetryDisableHelp": "Välj att inte skicka användningsinformation som hjälper Microsoft att förbättra den här produkten",
  "CliTelemetryDisabled": "Telemetrisamlingen är inaktiverad.",
  "CliTelemetryEnableHelp": "Välj att skicka användningsinformation som hjälper Microsoft att förbättra den här produkten",
  "CliTelemetryEnabled": "Telemetrisamlingen är aktiverad.",
  "CliTelemetryHelp": "Hantera telemetriinställningar",
  "CliTelemetryStatusDisabled": "Telemetri är för tillfället inaktiverat",
  "CliTelemetryStatusEnabled": "Telemetri är för tillfället aktiverat",
  "CliTelemetryStatusHelp": "Visa aktuell status för telemetri",
  "CommandDoesNotTakeArguments": "Det här kommandot använder inte några argument.",
  "CommandDoesNotTakeSubCommands": "Det här kommandot använder inte några underkommandon.",
  "CommandNotUnderstood": "Kommandot {0} fungerar i denna kontext.",
  "CommandsWithColon": "Kommandon: ",
  "ConnectedTo": "Ansluten till ...",
  "CorruptAuthToken": "Det går inte att läsa autentiseringstoken. Kör pac auth create för att skapa en ny token.",
  "CorruptedFeatureFlagsFile": "Funktionen flaggar att filen {0} är skadad.",
  "ErrorRunningTool": "Fel vid körning av verktyget: {0} med argumenten: {1}.",
  "ErrorWithColon": "Fel: ",
  "FileAt": "  Fil i {0}.",
  "FileNotFound": "Filen hittades inte: {0}",
  "HelpWithColon": "Hjälp: ",
  "HintsWithColon": "Tips: ",
  "InitFailure": "Det gick inte att skapa projektet {0}. Den aktuella katalogen innehåller redan ett projekt. Skapa en ny katalog och försök igen.",
  "IntegersOnlyRegexHelp": "Värdet måste vara ett positivt heltal",
  "InvalidArgumentValue": "Argumentvärdet {0} är felaktigt: {1}.",
  "InvalidArgumentValueLength": "Argumentet {0} har fel längd. Argumentets längd måste vara mellan {1} och {2}.",
  "InvalidProjectDirectoryName": "Tomt eller ogiltigt projektnamn {0}",
  "InvalidSwitchArgumentValue": "Värdet som skickades till {0} är ogiltigt. Om inget värde skickas får argumentet värdet true. Värden: true, false.",
  "MissingFeatureFlagsFile": "Funktionen flaggar att filen {0} saknas.",
  "MissingRequiredArgument": "Det obligatoriska argumentet {0} saknas.",
  "MissingRequiredTool": "Ett nödvändigt verktyg saknas: {0}. Lägg till {0} i miljövariabeln Path eller använd Developer Command Prompt for VS.",
  "MissingSubCommand": "Du saknar ett under kommando.",
  "NoResultsReturned": "Inga resultat returnerades.",
  "NoWasItMisspelled": "Nej, var det felstavat?",
  "NoWrapInQuotes": "Nej, se till att omsluta värden som innehåller blanksteg med citattecken.",
  "NoneInParenthesis": "(Ingen)",
  "NotValidCommand": "Detta är inte ett giltigt kommando. Försök köra {0} [command] help.",
  "OptionsWithColon": "Alternativ: ",
  "OrgConnectionFailed": "Det gick inte att ansluta till CDS-organisationen på {0}.",
  "OrgEntityEntityNameHelp": "Namnet på entiteten",
  "OrgEntityGetFieldsHeader": "{0} ({1}) Fält:",
  "OrgEntityGetFieldsHelp": "Visa fälten för en entitet",
  "OrgEntityGetFieldsLine": "{0} ({1})",
  "OrgEntityGetRecordsFieldNotValid": "Det gick inte att hitta fältet {0} i {1}. Du köra {2} {3} {4} {5} om du vill visa en lista med fält.",
  "OrgEntityGetRecordsFieldsHelp": "Lista över de fält för entiteten som ska hämtas (* för alla)",
  "OrgEntityGetRecordsHeader": "Postnr {0}",
  "OrgEntityGetRecordsHelp": "Visa en specifik post för en entitet",
  "OrgEntityGetRecordsIdHelp": "ID:t för posten som ska hämtas",
  "OrgEntityGetRecordsIdNotValid": "ID:t som skickades är inte ett giltigt Guid.",
  "OrgEntityHelp": "Hämta information om en entitet i CDS",
  "OrgFriendlyName": "Eget namn:",
  "OrgHelp": "Arbeta med din CDS-organisation",
  "OrgId": "Org-ID:",
  "OrgQueryHelp": "Visa resultaten från en fråga mot CDS",
  "OrgQueryRowHeader": "Radnr {0}",
  "OrgQuerySqlHelp": "SQL SELECT-frågan som ska köras",
  "OrgResultRow": "{0}: {1}",
  "OrgUniqueName": "Unikt namn:",
  "OrgUrl": "Organisationens URL:",
  "OrgUserId": "Användar-ID:",
  "OrgWhoHelp": "Visar information om den aktuella CDS-organisationen",
  "OrganizationInformation": "Organisationsinformation",
  "PCFPatchVersionUpdateStartegyHelp": "Uppdaterar korrigeringsversionen för kontrollmanifestfiler med hjälp av den angivna strategin. Om du använder gittags anger du en personlig åtkomsttoken i följande miljö variabel, \"PacCli.PAT\"",
  "PackageAddReference": "Lägger till referens till CDS-lösningsprojekt",
  "PackageAddReferencePathSwitch": "Sökvägen till det refererade CDS-lösningsprojektet",
  "PackageAddReferenceSuccess": "CDS-projektreferensen har lagts till i paketet.",
  "PackageHelp": "Kommandon som används för att arbeta med CDS-paketprojekt",
  "PackageInitHelp": "Initierar en katalog med ett nytt CDS-paketprojekt",
  "PackageInitSuccess": "CDS-paketet skapades i {0}.",
  "ParseExceptionCurrentCommand": "Aktuellt kommando:",
  "ParseExceptionFailedOn": "Parsning misslyckades för:",
  "ParseExceptionKnownArgument": "Är detta ett känt argument?",
  "ParseExceptionKnownCommand": "Är detta ett känt kommando?",
  "ParseExceptionQuoteWrapped": "Var det omslutet med citattecken?",
  "PathIsNotValid": "Sökvägen {0} är inte en giltig sökväg.",
  "PcfCommitIDError": "Det gick inte att hämta det senaste genomförande-ID:t för kontrollen: {0}",
  "PcfControlFolderNameParseError": "Det går inte att parsa rotmappnamnet för kontrollen: {0}",
  "PcfControlManifestNotFound": "Det gick inte att hitta filen ControlManifest.Input.xml på {0}.",
  "PcfControlManifestPathHelp": "Absolut/relativ sökväg för kontrollmanifestfilen som ska uppdateras.",
  "PcfControlManifestTooManyFound": "Det finns flera ControlManifest.Input.xml-filer på {0}.",
  "PcfControlNoChangeInResource": "Inga ändringar hittades i {0}.",
  "PcfControlNotAGitRepo": "Projektet är inte en giltig Git-databas",
  "PcfControlUpdatingResource": "Uppdaterar {0}.",
  "PcfControlVersionFileInvalidContent": "Ogiltigt innehåll hittades i {0}",
  "PcfDiscoverAllManifestFilesHelp": "Uppdaterar korrigeringsversionen för alla kontrollmanifestfiler",
  "PcfHashControlVersionNotMatching": "Hash-kontrollversion i {0} har inte format för parsning som stöds",
  "PcfHelp": "Kommandon som används för att arbeta med PowerApps component framework-projekt",
  "PcfIncludesReservedWord": "Värdet {0} som skickats för ett argument är eller innehåller ett reserverat ord.",
  "PcfInitHelp": "Initierar en katalog med ett nytt PowerApps component framework-projekt",
  "PcfInitNameHelp": "Namnet på komponenten",
  "PcfInitNameRegexHelp": "Endast tecken inom intervallen [A–Z], [a–z] eller [0–9] tillåts. Det första tecknet får inte vara ett tal.",
  "PcfInitNamespaceHelp": "Namnrymden för komponenten",
  "PcfInitNamespaceRegexHelp": "Endast tecken inom intervallen [A–Z], [a–z], [0–9] eller \".\" tillåts. Det första och sista tecknet får inte vara tecknet \".\" Flera \".\"-tecken i rad tillåts inte. Tal får inte vara det första tecknet eller komma omedelbart efter en punkt.",
  "PcfInitSuccessLine1": "PowerApps component framework-projektet har skapats i {0}.",
  "PcfInitSuccessLine2": "Kör npm install i den här katalogen om du vill installera projektberoenden.",
  "PcfInitTemplateHelp": "Välj en mall för komponenten",
  "PcfInvalidGitPAT": "En privat åtkomsttoken som används för att skicka taggar till fjärrursprung är ogiltig eller saknas i miljövariabeln {0}",
  "PcfMaximumLengthExceeded": "Den totala längden för argumenten {0} och {1} får inte överskrida {2}.",
  "PcfNoManifestFilesFound": "{0}-filer finns inte i någon av mapparna i {1}.",
  "PcfNoVersionAttribute": "{0} saknar ett versionsattribut.",
  "PcfPatchVersionAdditionalCommandsWithStrategy": "Strategiargument kräver inte {0}. Alla nödvändiga manifestfiler uppdateras.",
  "PcfPatchVersionHelp": "Korrigeringsversion för kontroller",
  "PcfPatchVersionUpdateDirectoryHelp": "Ange vilket målmanifest som måste uppdateras",
  "PcfProjectNotFound": "Projektfilen för PowerApps component framework med tillägget pcfproj finns inte i katalogen {0}.",
  "PcfProjectTooManyFound": "Flera pcfproj-filer hittades på {0}.",
  "PcfPushBuildExeNotFound": "Det gick inte att hitta dotnet.exe eller msbuild.exe för att skapa den temporära lösningen.",
  "PcfPushBuildingTempSolution": "Skapar omslutningen till den temporära lösningen.",
  "PcfPushCheckingResources": "Söker efter ändringar av respektive resurs.",
  "PcfPushComparingControlManifests": "Jämför manifestet i den aktuella organisationen med manifestet på {0}.",
  "PcfPushControlManifestsDifferent": "Kontrollmanifesten skiljer sig åt.",
  "PcfPushControlManifestsEqual": "Kontrollmanifesten är desamma.",
  "PcfPushControlNotFound": "Det gick inte att hitta kontrollen i den aktuella organisationen.",
  "PcfPushDoesControlExistOnOrg": "Kontrollerar om kontrollen {0} redan finns i den aktuella organisationen.",
  "PcfPushDone": "Uppdaterar kontrollen i den aktuella organisationen: klart.",
  "PcfPushForceImportHelp": "Framtvinga en fullständig uppdatering av kontrollen",
  "PcfPushHelp": "Importera PowerApps component framework-projektet till den aktuella CDS-organisationen",
  "PcfPushLoadingControlFromOrg": "Kontrollen finns i den aktuella organisationen, läser in kontrollens information.",
  "PcfPushLocatingResources": "Söker efter de webbresurser som används av kontrollen {0}.",
  "PcfPushOnlySupportsUnmanaged": "Kontrollen finns i det aktuella organisationen men är hanterad. Kommandot {0} fungerar bara mot ohanterade kontroller.",
  "PcfPushTempSolutionBuildFailed": "Bygger en omslutning för den tillfälliga lösningen: Misslyckades. Se {0} för mer information.",
  "PcfPushTempSolutionBuildSucceeded": "Bygger omslutningen för den tillfälliga lösningen: Klart.",
  "PcfPushTempSolutionCreated": "Skapar omslutningen för den tillfälliga lösningen: Klart.",
  "PcfPushTempSolutionCreating": "Skapar en omslutning för den tillfälliga lösningen för att skicka komponenten.",
  "PcfPushTempSolutionCreationFailed": "Skapar en omslutning för den tillfälliga lösningen: Misslyckades. I loggarna finns mer information.",
  "PcfPushTempSolutionDoneImport": "Importerar omslutningen för den tillfälliga lösningen till den aktuella organisationen: Klart.",
  "PcfPushTempSolutionStartImport": "Importerar omslutningen för den tillfälliga lösningen till den aktuella organisationen.",
  "PcfPushTempSolutionZipDropped": "Släpper omslutningen för den tillfälliga lösningens zip-fil: Klart.",
  "PcfPushUnknownError": "Ett fel uppstod vid kontrollen av aktuell organisation: {0}. Återgår till fullständig uppdatering.",
  "PcfPushUsingFullUpdate": "Med fullständig uppdatering.",
  "PcfPushUsingIncrementalUpdate": "Med stegvis uppdatering.",
  "PcfPushVerbosityHelp": "Utförlighetsnivå för MSBuild när omslutningen för den tillfälliga lösningen byggs.",
  "PcfTagRegExNotMatching": "Taggnamnet har inte rätt format för kontrollen med följande information. ControlName: {0}, CommitID: {1}, Version: {2}",
  "PcfUpdatedControlManifestFilePath": "Korrigeringsversionen har uppdaterats för {0}.",
  "PcfVersionDone": "Korrigeringsversionen för de angivna kontrollmanifestfilerna är klar.",
  "PluginHelp": "Kommandon som används för att arbeta med klassbibliotek för plugin-programmet CDS",
  "PluginInitHelp": "Initierar en katalog med ett nytt klassbibliotek för plugin-programmet CDS.",
  "PluginInitSigningKeyFilePathHelp": "Relativ sökväg till upphovsmannens nyckelfil för signering för paketet med plugin-programmet CDS.",
  "PluginInitSigningKeyFilePathValidationHelp": "Detta är inte ett giltigt tillägg för nyckelfilen: {0}. Ange en giltig fil av formatet .snk eller .pfx för paketet med plugin-programmet CDS.",
  "PluginInitSuccess": "Klassbiblioteket med namnet {0} för plugin-programmet CDS har skapats i den aktuella katalogen.",
  "PortalAppsHelp": "Kommandon som visar en lista med appar och antalet nedladdningar för aktuell användare",
  "PortalAppsResult": "Lista med alla appar för {0}",
  "PortalHelp": "Kommandon för att arbeta med onlinetjänsten PowerApps Studio",
  "PortalPublisherResult": "Lista med utgivare för {0}",
  "PortalPubsVerb": "Kommandon för att visa en lista med utgivare för aktuell användare",
  "ReferenceNoProjectsFound": "Det finns ingen projekttyp som stöds i sökvägen {0}.",
  "ReferenceTooManyProjectsFound": "Det finns fler än en projekttyp som stöds i sökvägen {0}.",
  "SolutionAddReferenceFailure": "Det går inte att lägga till en referens till ett projekt med samma namn som CDS-projektet med namnet: {0}.",
  "SolutionAddReferenceHelp": "Lägger till en referens från projektet i den aktuella katalogen till projektet i path",
  "SolutionAddReferencePathHelp": "Sökvägen till det refererade projektet",
  "SolutionAddReferenceSuccess": "Projektreferensen har lagts till i CDS-lösningsprojektet.",
  "SolutionCloneErrorFolderExists": "Lösningsmappen finns redan och är inte tom.",
  "SolutionCloneExtractSucceeded": "Lösningen har extraherats.",
  "SolutionCloneHelp": "Skapa ett lösningsprojekt baserat på en befintlig lösning i din organisation",
  "SolutionCloneManagedExportSucceeded": "Den hanterade lösningen har exporterats.",
  "SolutionCloneUnmanagedExportSucceeded": "Den ohanterade lösningen har exporterats.",
  "SolutionExportErrorFileExists": "Utdatafilen {0} för lösningen finns redan.",
  "SolutionExportErrorInvalidPath": "{0} är en ogiltig sökväg. {1}",
  "SolutionExportHelp": "Exportera ett CDS-lösningsprojekt från den aktuella CDS-organisationen",
  "SolutionExportIncludeHelp": "Vilka inställningar ska ingå i lösningen som exporteras",
  "SolutionExportManagedHelp": "Om lösningen ska exporteras som en hanterad lösning",
  "SolutionExportNameHelp": "Namnet på lösningen som ska exporteras",
  "SolutionExportPathHelp": "Sökväg där den exporterade lösningens zip-fil sparas",
  "SolutionExportSucceeded": "Lösningen har exporterats.",
  "SolutionExportTargetVersionHelp": "Den version som den exporterade lösningen kommer att stödja",
  "SolutionHelp": "Kommandon som används för att arbeta med CDS-lösningsprojekt",
  "SolutionImportActivatePluginsHelp": "Aktivera plugin-program och arbetsflöden i lösningen",
  "SolutionImportAsHoldingHelp": "Importera lösningen som en förvaringslösning",
  "SolutionImportHelp": "Importera CDS-lösningsprojektets utdata till den aktuella CDS-organisationen",
  "SolutionImportOverwriteUnmanagedHelp": "Framtvinga en överskrivning av ohanterade anpassningar",
  "SolutionImportPathHelp": "Sökväg till lösningens zip-fil. Behövs inte om du kör från platsen cdsproj.",
  "SolutionImportPublishHelp": "Publicera dina ändringar när importen har genomförts",
  "SolutionImportSkipDependencyHelp": "Hoppa över beroendekontrollen av beroenden som flaggas som produktuppdatering",
  "SolutionInitAssetSuccessLine1": "CDS-lösningsfiler har skapats för det här projektet i underkatalogen {0} med lösningsnamnet {1}, utgivarnamnet {2} och anpassningsprefixet {3}.",
  "SolutionInitAssetSuccessLine2": "Kontrollera utgivarens information och lösningsnamnet som finns i filen {0}.",
  "SolutionInitCustomizationPrefixHelp": "Värdet på anpassningsprefixet för utgivaren av CDS-lösningen",
  "SolutionInitCustomizationPrefixRegexHelp": "Prefixet måste vara 2–8 tecken långt, kan bara bestå av alfanumeriska tecken, måste börja med en bokstav och kan inte börja med mscrm.",
  "SolutionInitExistingProject": "Det finns redan CDS-lösningsfiler i den aktuella katalogen. Hoppa över att skapa CDS-lösningsfiler.",
  "SolutionInitHelp": "Initierar en katalog med ett nytt CDS-lösningsprojekt",
  "SolutionInitPublisherNameHelp": "Namn på utgivaren av CDS-lösningen",
  "SolutionInitPublisherNameRegexHelp": "Endast tecken inom intervallen [A–Z], [a–z], [0–9] eller _ tillåts. Det första tecknet måste ligga inom intervallen [A–Z], [a–z] eller vara _.",
  "SolutionInitSuccess": "CDS-lösningsprojektet med namnet {0} har skapats i den aktuella katalogen.",
  "SolutionInitTooManyOtherDirectories": "Det finns ytterligare en katalog, {0}, för CDS-lösningar. Behåll bara en katalog.",
  "SolutionInitTooManySolutionXmlFiles": "Det finns flera {0}-filer i {1}.",
  "SolutionMultipleProjectsFound": "Det finns flera projektfiler med tillägget {0} i katalogen {1}.",
  "SolutionProjectNotFound": "Filen med CDS-lösningsprojektet med tillägget cdsproj finns inte i katalogen {0}.",
  "SolutionZipNotFound": "Du måste antingen använda argumentet {0} eller köra kommandot {1} inifrån CDS-lösningens projektkatalog.",
  "UnhandledExceptionMessage": "Appen har tyvärr påträffat ett oåterkalleligt fel och måste avslutas. Undantagsinformation har samlats in och vidarebefordrats till utvecklingsteamet om telemetri har aktiverats. Undantags-ID:",
  "UnknownArgument": "Det okända argumentet {0} har skickats.",
  "UnknownArgumentValue": "Det okända argumentvärdet för {0} har skickats.",
  "UnknownCommand": "Det okända kommandot {0} har skickats.",
  "UnneededArgument": "Ett onödigt argument har skickats.",
  "UsageWithColon": "Användning: {0}",
  "ValuesWithColon": "Värden: ",
  "VersionWithColon": "Version: {0}",
  "WarningWithColon": "Varning: ",
  "Yes": "Ja"
}